geoseeq/__init__.py
geoseeq/app.py
geoseeq/blob_constructors.py
geoseeq/bulk_creators.py
geoseeq/constants.py
geoseeq/file_system_cache.py
geoseeq/knex.py
geoseeq/organization.py
geoseeq/pipeline.py
geoseeq/project.py
geoseeq/remote_object.py
geoseeq/sample.py
geoseeq/search.py
geoseeq/smart_table.py
geoseeq/smart_tree.py
geoseeq/upload_download_manager.py
geoseeq/user.py
geoseeq/utils.py
geoseeq/work_orders.py
geoseeq/cli/__init__.py
geoseeq/cli/constants.py
geoseeq/cli/copy.py
geoseeq/cli/detail.py
geoseeq/cli/download.py
geoseeq/cli/fastq_utils.py
geoseeq/cli/find_grn.py
geoseeq/cli/get_eula.py
geoseeq/cli/main.py
geoseeq/cli/manage.py
geoseeq/cli/progress_bar.py
geoseeq/cli/project.py
geoseeq/cli/raw.py
geoseeq/cli/run.py
geoseeq/cli/search.py
geoseeq/cli/user.py
geoseeq/cli/utils.py
geoseeq/cli/view.py
geoseeq/cli/shared_params/__init__.py
geoseeq/cli/shared_params/common_state.py
geoseeq/cli/shared_params/config.py
geoseeq/cli/shared_params/id_handlers.py
geoseeq/cli/shared_params/obj_getters.py
geoseeq/cli/shared_params/opts_and_args.py
geoseeq/cli/upload/__init__.py
geoseeq/cli/upload/upload.py
geoseeq/cli/upload/upload_advanced.py
geoseeq/cli/upload/upload_reads.py
geoseeq/contrib/__init__.py
geoseeq/contrib/ncbi/README.md
geoseeq/contrib/ncbi/__init__.py
geoseeq/contrib/ncbi/api.py
geoseeq/contrib/ncbi/bioproject.py
geoseeq/contrib/ncbi/cli.py
geoseeq/contrib/ncbi/setup_logging.py
geoseeq/dashboard/dashboard.py
geoseeq/file_system/filesystem_download.py
geoseeq/file_system/main.py
geoseeq/id_constructors/__init__.py
geoseeq/id_constructors/from_blobs.py
geoseeq/id_constructors/from_ids.py
geoseeq/id_constructors/from_names.py
geoseeq/id_constructors/from_uuids.py
geoseeq/id_constructors/resolvers.py
geoseeq/id_constructors/utils.py
geoseeq/plotting/README.md
geoseeq/plotting/__init__.py
geoseeq/plotting/constants.py
geoseeq/plotting/highcharts.py
geoseeq/plotting/selectable.py
geoseeq/plotting/map/__init__.py
geoseeq/plotting/map/base_layer.py
geoseeq-0.7.11.dist-info/METADATA
geoseeq-0.7.11.dist-info/WHEEL
geoseeq-0.7.11.dist-info/entry_points.txt
geoseeq-0.7.11.dist-info/licenses/LICENSE
geoseeq-0.7.11.dist-info/RECORD
