Metadata-Version: 2.4
Name: geoseeq
Version: 0.7.11
Summary: GeoSeeq command line tools and python API
Project-URL: Homepage, https://github.com/biotia/geoseeq_api_client
Project-URL: Issues, https://github.com/biotia/geoseeq_api_client/issues
Author-email: "David C. Danko" <dcdanko@biotia.io>
License-File: LICENSE
Classifier: License :: OSI Approved :: MIT License
Classifier: Operating System :: OS Independent
Classifier: Programming Language :: Python :: 3
Requires-Python: >=3.8
Requires-Dist: biopython
Requires-Dist: click
Requires-Dist: pandas
Requires-Dist: requests
Requires-Dist: tqdm
Provides-Extra: test
Requires-Dist: pytest-cov>=4.0; extra == 'test'
Requires-Dist: pytest-mock>=3.10; extra == 'test'
Requires-Dist: pytest>=7.0; extra == 'test'
Requires-Dist: requests-mock>=1.11; extra == 'test'
